juraHP/__init__.py
juraHP/ap_connector.py
juraHP/ap_generator.py
juraHP/hp_connector.py
juraHP/hp_generator.py
juraHP/master_connector.py
juraHP/robot.py
juraHP-1.1.dist-info/METADATA
juraHP-1.1.dist-info/WHEEL
juraHP-1.1.dist-info/top_level.txt
juraHP-1.1.dist-info/RECORD
