Metadata-Version: 2.1
Name: juraHP
Version: 1.1
Summary: SSH Client Framework for HP/Cisco AeroNet Interface Renaming
Home-page: https://johnnes-smarts.ch
Author: David Johnnes
Author-email: david.johnnes@gmail.com
License: License :: OSI Approved :: MIT License
Keywords: SSH Client,Network Automation
Platform: UNKNOWN
Classifier: Programming Language :: Python :: 3
Classifier: License :: OSI Approved :: MIT License
Classifier: Operating System :: OS Independent
